shade/__init__.py
shade/enums.py
shade/query_builder.py
shade/resources/__init__.py
shade/resources/abc_resource.py
shade/resources/asset.py
shade/resources/billing.py
shade/resources/drive.py
shade/resources/file.py
shade/resources/share.py
shade/resources/workspace.py
shade/utils.py
shade_python_sdk-1.0.2.dist-info/LICENSE
shade_python_sdk-1.0.2.dist-info/METADATA
shade_python_sdk-1.0.2.dist-info/WHEEL
shade_python_sdk-1.0.2.dist-info/entry_points.txt
shade_python_sdk-1.0.2.dist-info/RECORD
