Metadata-Version: 2.1
Name: shade-python-sdk
Version: 1.0.2
Summary: Shade SDK
License: MIT
Author: Shade
Author-email: shade@shade.inc
Requires-Python: >=3.10,<4.0
Classifier: License :: OSI Approved :: MIT License
Classifier: Programming Language :: Python :: 3
Classifier: Programming Language :: Python :: 3.10
Classifier: Programming Language :: Python :: 3.11
Classifier: Programming Language :: Python :: 3.12
Requires-Dist: dataclass-wizard (>=0.22.2,<0.23.0)
Requires-Dist: pillow (>=10.4.0,<11.0.0)
Requires-Dist: pre-commit (>=4.0.1,<5.0.0)
Requires-Dist: pydantic (>=2.4.2,<3.0.0)
Requires-Dist: pytest (>=8.0.0,<9.0.0)
Requires-Dist: requests (>=2.31.0,<3.0.0)
Requires-Dist: ruff (>=0.7.4,<0.8.0)
